django_threaded_email/__init__.py
django_threaded_email/django_threaded_email.py
django_threaded_email-0.0.1.dist-info/LICENSE
django_threaded_email-0.0.1.dist-info/METADATA
django_threaded_email-0.0.1.dist-info/WHEEL
django_threaded_email-0.0.1.dist-info/top_level.txt
django_threaded_email-0.0.1.dist-info/RECORD
