Metadata-Version: 2.1
Name: django-threaded-email
Version: 0.0.1
Summary: Send an email in the background using the builtin threading module.
Home-page: https://github.com/MrThearMan/django-threaded-email
Author: Matti Lamppu
Author-email: lamppu.matti.akseli@gmail.com
License: UNKNOWN
Project-URL: Bug Tracker, https://github.com/MrThearMan/django-threaded-email/issues
Platform: UNKNOWN
Classifier: Programming Language :: Python :: 3
Classifier: License :: OSI Approved :: MIT License
Classifier: Operating System :: OS Independent
Requires-Python: >=3.8
